{"type":"FeatureCollection","features":[{"type":"Feature","id":1,"geometry":{"type":"Point","coordinates":[-116.56757919999995,47.314659520000077]},"properties":{"OBJECTID":1,"Facility":"Benewah Community Hospital","Address":"229 South 7th","City":"St. Maries","State":"Idaho","Zip":83861,"Telephone":"(208) 245-5551","Critical_Access_Hospital":"X","Births_in_2022":null,"Region":1,"Community":"St. Maries","Note":"EMERGENCIES ONLY","Website":"http://www.bchmed.org","Latitude":47.314659519999999,"Longitude":-116.5675792,"Field15":null}},{"type":"Feature","id":2,"geometry":{"type":"Point","coordinates":[-111.10801999999995,43.727200000000039]},"properties":{"OBJECTID":2,"Facility":"Teton Valley Health Care Inc.","Address":"120 East Howard Avenue","City":"Driggs","State":"Idaho","Zip":83422,"Telephone":"(208) 354-2383","Critical_Access_Hospital":"X","Births_in_2022":null,"Region":7,"Community":"Driggs","Note":"EMERGENCIES ONLY","Website":"https://tvhcare.org","Latitude":43.727200000000003,"Longitude":-111.10802,"Field15":null}}]}